<?xml version="1.0" ?>
<!DOCTYPE PubmedArticleSet PUBLIC "-//NLM//DTD PubMedArticle, 1st January 2025//EN" "https://dtd.nlm.nih.gov/ncbi/pubmed/out/pubmed_250101.dtd">
<PubmedArticleSet>
<PubmedArticle><MedlineCitation Status="MEDLINE" Owner="NLM" IndexingMethod="Automated"><PMID Version="1">41725778</PMID><DateCompleted><Year>2026</Year><Month>02</Month><Day>23</Day></DateCompleted><DateRevised><Year>2026</Year><Month>02</Month><Day>23</Day></DateRevised><Article PubModel="Electronic-eCollection"><Journal><ISSN IssnType="Electronic">2296-2565</ISSN><JournalIssue CitedMedium="Internet"><Volume>14</Volume><PubDate><Year>2026</Year></PubDate></JournalIssue><Title>Frontiers in public health</Title><ISOAbbreviation>Front Public Health</ISOAbbreviation></Journal><ArticleTitle>Exercise interventions for sleep and cognitive dysfunction in shift workers: a systematic review of randomized trials.</ArticleTitle><Pagination><StartPage>1762359</StartPage><MedlinePgn>1762359</MedlinePgn></Pagination><ELocationID EIdType="pii" ValidYN="Y">1762359</ELocationID><ELocationID EIdType="doi" ValidYN="Y">10.3389/fpubh.2026.1762359</ELocationID><Abstract><AbstractText Label="BACKGROUND AND OBJECTIVES" NlmCategory="UNASSIGNED">Shift work disrupts circadian rhythms and contributes to poor sleep, cardiometabolic risk, and cognitive impairment, which is especially concerning in safety-critical professions. While exercise improves sleep and cognition in the general population, its effects in shift-working adults remain unclear. This review synthesizes randomized controlled trials (RCT) evidence on structured exercise training to determine its impact on sleep and cognitive outcomes in shift workers, and examines intervention characteristics, mechanistic pathways, and barriers to clinical translation.</AbstractText><AbstractText Label="MATERIALS AND METHODS" NlmCategory="UNASSIGNED">Following PRISMA and Cochrane recommendations, six databases were searched from inception to January 2025 for RCTs involving adult shift workers and structured exercise (aerobic, resistance, combined, HIIT, or in-shift activity breaks). Primary outcomes were sleep quality, quantity, and continuity assessed using the Pittsburgh Sleep Quality Index (PSQI), actigraphy or polysomnography, and the Karolinska Sleepiness Scale (KSS), as well as cognitive performance and alertness measured by the Psychomotor Vigilance Task (PVT). Risk of bias (RoB 2.0) and methodological quality (PEDro) were assessed. Due to heterogeneity in interventions and outcome measures, results were narratively synthesized.</AbstractText><AbstractText Label="RESULTS" NlmCategory="UNASSIGNED">Ten RCTs (<i>n</i>&#x202f;=&#x202f;420; 60% healthcare settings) predominantly evaluated aerobic or mixed modalities. Eight studies reported significant improvements in PSQI, total sleep time, sleep efficiency, or wake after sleep onset, although effect sizes and clinical relevance were inconsistent. Three RCTs demonstrated improvements in alertness, reaction time, and short-term memory, particularly when interventions were timed post-shift or delivered as supervised workplace sessions. Mechanistic evidence from six studies indicated circadian phase shifting, improved autonomic balance assessed by heart rate variability (HRV), and reduced inflammatory markers. However, 80% had "some concerns" or "high" risk of bias, and adherence barriers such as fatigue and irregular schedules were common.</AbstractText><AbstractText Label="CONCLUSION" NlmCategory="UNASSIGNED">Structured exercise programs, tailored to shift pattern and individual chronotype, show promise for enhancing sleep and cognitive function in shift workers. Workplace-based, supervised interventions maximize adherence and real-world applicability. Future adequately powered RCTs with standardized outcomes, mechanistic markers, and sector-diverse samples are needed before guideline-level recommendations can be established.</AbstractText><AbstractText Label="SYSTEMATIC REVIEW REGISTRATION" NlmCategory="UNASSIGNED">Identifier, PROSPERO CRD420250650538. https://www.crd.york.ac.uk/PROSPERO/view/CRD420250650538.</AbstractText><CopyrightInformation>Copyright &#xa9; 2026 Algharbi, Nuhmani, Alsubaiei, Shanb and Alquaimi.</CopyrightInformation></Abstract><AuthorList CompleteYN="Y"><Author ValidYN="Y"><LastName>Algharbi</LastName><ForeName>Fahad Hamoud</ForeName><Initials>FH</Initials><AffiliationInfo><Affiliation>Department of Physiotherapy, College of Applied Medical Sciences, Imam Abdulrahman bin Faisal University, Dammam, Saudi Arabia.</Affiliation></AffiliationInfo><AffiliationInfo><Affiliation>Medical Support Services, Royal Commission Health Services Program, Royal Commission for Jubail and Yanbu, Jubail, Saudi Arabia.</Affiliation></AffiliationInfo></Author><Author ValidYN="Y"><LastName>Nuhmani</LastName><ForeName>Shibili</ForeName><Initials>S</Initials><AffiliationInfo><Affiliation>Department of Physiotherapy, College of Applied Medical Sciences, Imam Abdulrahman bin Faisal University, Dammam, Saudi Arabia.</Affiliation></AffiliationInfo></Author><Author ValidYN="Y"><LastName>Alsubaiei</LastName><ForeName>Mohammed</ForeName><Initials>M</Initials><AffiliationInfo><Affiliation>Department of Physiotherapy, College of Applied Medical Sciences, Imam Abdulrahman bin Faisal University, Dammam, Saudi Arabia.</Affiliation></AffiliationInfo></Author><Author ValidYN="Y"><LastName>Shanb</LastName><ForeName>Alsayed</ForeName><Initials>A</Initials><AffiliationInfo><Affiliation>Department of Physiotherapy, College of Applied Medical Sciences, Imam Abdulrahman bin Faisal University, Dammam, Saudi Arabia.</Affiliation></AffiliationInfo></Author><Author ValidYN="Y"><LastName>Alquaimi</LastName><ForeName>Maher</ForeName><Initials>M</Initials><AffiliationInfo><Affiliation>Department of Respiratory Therapy, College of Applied Medical Sciences, Imam Abdulrahman bin Faisal University, Dammam, Saudi Arabia.</Affiliation></AffiliationInfo></Author></AuthorList><Language>eng</Language><PublicationTypeList><PublicationType UI="D016428">Journal Article</PublicationType><PublicationType UI="D000078182">Systematic Review</PublicationType></PublicationTypeList><ArticleDate DateType="Electronic"><Year>2026</Year><Month>02</Month><Day>06</Day></ArticleDate></Article><MedlineJournalInfo><Country>Switzerland</Country><MedlineTA>Front Public Health</MedlineTA><NlmUniqueID>101616579</NlmUniqueID><ISSNLinking>2296-2565</ISSNLinking></MedlineJournalInfo><CitationSubset>IM</CitationSubset><MeshHeadingList><MeshHeading><DescriptorName UI="D006801" MajorTopicYN="N">Humans</DescriptorName></MeshHeading><MeshHeading><DescriptorName UI="D016032" MajorTopicYN="N">Randomized Controlled Trials as Topic</DescriptorName></MeshHeading><MeshHeading><DescriptorName UI="D060825" MajorTopicYN="Y">Cognitive Dysfunction</DescriptorName><QualifierName UI="Q000628" MajorTopicYN="N">therapy</QualifierName></MeshHeading><MeshHeading><DescriptorName UI="D015444" MajorTopicYN="Y">Exercise</DescriptorName><QualifierName UI="Q000502" MajorTopicYN="N">physiology</QualifierName></MeshHeading><MeshHeading><DescriptorName UI="D000328" MajorTopicYN="N">Adult</DescriptorName></MeshHeading><MeshHeading><DescriptorName UI="D000073577" MajorTopicYN="Y">Shift Work Schedule</DescriptorName></MeshHeading><MeshHeading><DescriptorName UI="D012890" MajorTopicYN="Y">Sleep</DescriptorName><QualifierName UI="Q000502" MajorTopicYN="N">physiology</QualifierName></MeshHeading></MeshHeadingList><KeywordList Owner="NOTNLM"><Keyword MajorTopicYN="N">circadian rhythms</Keyword><Keyword MajorTopicYN="N">cognitive function</Keyword><Keyword MajorTopicYN="N">exercise</Keyword><Keyword MajorTopicYN="N">night shift</Keyword><Keyword MajorTopicYN="N">shift work</Keyword><Keyword MajorTopicYN="N">sleep quality</Keyword></KeywordList><CoiStatement>The author(s) declared that this work was conducted in the absence of any commercial or financial relationships that could be construed as a potential conflict of interest.</CoiStatement></MedlineCitation><PubmedData><History><PubMedPubDate PubStatus="received"><Year>2025</Year><Month>12</Month><Day>7</Day></PubMedPubDate><PubMedPubDate PubStatus="revised"><Year>2026</Year><Month>1</Month><Day>11</Day></PubMedPubDate><PubMedPubDate PubStatus="accepted"><Year>2026</Year><Month>1</Month><Day>16</Day></PubMedPubDate><PubMedPubDate PubStatus="medline"><Year>2026</Year><Month>2</Month><Day>23</Day><Hour>13</Hour><Minute>6</Minute></PubMedPubDate><PubMedPubDate PubStatus="pubmed"><Year>2026</Year><Month>2</Month><Day>23</Day><Hour>13</Hour><Minute>5</Minute></PubMedPubDate><PubMedPubDate PubStatus="entrez"><Year>2026</Year><Month>2</Month><Day>23</Day><Hour>6</Hour><Minute>16</Minute></PubMedPubDate><PubMedPubDate PubStatus="pmc-release"><Year>2026</Year><Month>2</Month><Day>6</Day></PubMedPubDate></History><PublicationStatus>epublish</PublicationStatus><ArticleIdList><ArticleId IdType="pubmed">41725778</ArticleId><ArticleId IdType="pmc">PMC12920463</ArticleId><ArticleId IdType="doi">10.3389/fpubh.2026.1762359</ArticleId></ArticleIdList><ReferenceList><Reference><Citation>Wickwire EM, Geiger-Brown J, Scharf SM, Drake CL. Shift work and shift work sleep disorder: clinical and organizational perspectives. Chest. (2017) 151:1156&#x2013;72. doi: 10.1016/j.chest.2016.12.007,</Citation><ArticleIdList><ArticleId IdType="doi">10.1016/j.chest.2016.12.007</ArticleId><ArticleId IdType="pmc">PMC6859247</ArticleId><ArticleId IdType="pubmed">28012806</ArticleId></ArticleIdList></Reference><Reference><Citation>Morris CJ, Purvis TE, Hu K, Scheer FA. Circadian misalignment increases cardiovascular disease risk factors in humans. Proc Natl Acad Sci USA. (2016) 113:E1402&#x2013;11. doi: 10.1073/pnas.1516953113,</Citation><ArticleIdList><ArticleId IdType="doi">10.1073/pnas.1516953113</ArticleId><ArticleId IdType="pmc">PMC4790999</ArticleId><ArticleId IdType="pubmed">26858430</ArticleId></ArticleIdList></Reference><Reference><Citation>Alfonsi V, Scarpelli S, D&#x2019;Atri A, Stella G, De Gennaro L. Later school start time: the impact of sleep on academic performance and health in the adolescent population. Int J Environ Res Public Health. (2020) 17:2574. doi: 10.3390/ijerph17072574</Citation><ArticleIdList><ArticleId IdType="doi">10.3390/ijerph17072574</ArticleId><ArticleId IdType="pmc">PMC7177233</ArticleId><ArticleId IdType="pubmed">32283688</ArticleId></ArticleIdList></Reference><Reference><Citation>Anbazhagan S, Ramesh N, Nisha C, Joseph B. Shift work disorder and related health problems among nurses working in a tertiary care hospital, Bangalore, South India. Indian J Occup Environ Med. (2016) 20:35&#x2013;8. doi: 10.4103/0019-5278.183842,</Citation><ArticleIdList><ArticleId IdType="doi">10.4103/0019-5278.183842</ArticleId><ArticleId IdType="pmc">PMC4922274</ArticleId><ArticleId IdType="pubmed">27390478</ArticleId></ArticleIdList></Reference><Reference><Citation>Vlasak T, Dujlovic T, Barth A. Neurocognitive impairment in night and shift workers: a meta-analysis of observational studies. Occup Environ Med. (2022) 79:365&#x2013;72. doi: 10.1136/oemed-2021-107847,</Citation><ArticleIdList><ArticleId IdType="doi">10.1136/oemed-2021-107847</ArticleId><ArticleId IdType="pubmed">35260480</ArticleId></ArticleIdList></Reference><Reference><Citation>Wong R, Crane A, Sheth J, Mayrovitz HN. Shift work as a cardiovascular disease risk factor: a narrative review. Cureus. (2023) 15:e41186. doi: 10.7759/cureus.41186,</Citation><ArticleIdList><ArticleId IdType="doi">10.7759/cureus.41186</ArticleId><ArticleId IdType="pmc">PMC10387224</ArticleId><ArticleId IdType="pubmed">37525789</ArticleId></ArticleIdList></Reference><Reference><Citation>Alruwaili A, Alanazy ARM. The effect of shift work on sleep patterns of paramedics in Saudi Arabia. J Multidiscip Healthc. (2024) 17:2857&#x2013;69. doi: 10.2147/JMDH.S458512,</Citation><ArticleIdList><ArticleId IdType="doi">10.2147/JMDH.S458512</ArticleId><ArticleId IdType="pmc">PMC11180460</ArticleId><ArticleId IdType="pubmed">38881751</ArticleId></ArticleIdList></Reference><Reference><Citation>Shiffer D, Minonzio M, Dipaola F, Bertola M, Zamuner AR, Dalla Vecchia LA, et al. Effects of clockwise and counterclockwise job shift work rotation on sleep and work-life balance on hospital nurses. Int J Environ Res Public Health. (2018) 15:2038. doi: 10.3390/ijerph15092038</Citation><ArticleIdList><ArticleId IdType="doi">10.3390/ijerph15092038</ArticleId><ArticleId IdType="pmc">PMC6164402</ArticleId><ArticleId IdType="pubmed">30231514</ArticleId></ArticleIdList></Reference><Reference><Citation>Leso V, Fontana L, Caturano A, Vetrani I, Fedele M, Iavicoli I. Impact of shift work and long working hours on worker cognitive functions: current evidence and future research needs. Int J Environ Res Public Health. (2021) 18:6540. doi: 10.3390/ijerph18126540</Citation><ArticleIdList><ArticleId IdType="doi">10.3390/ijerph18126540</ArticleId><ArticleId IdType="pmc">PMC8296479</ArticleId><ArticleId IdType="pubmed">34204504</ArticleId></ArticleIdList></Reference><Reference><Citation>Aljuaid M, Alajman N, Alsafadi A, Alnajjar F, Alshaikh M. Medication error during the day and night shift on weekdays and weekends: a single teaching hospital experience in Riyadh, Saudi Arabia. Risk Manag Healthc Policy. (2021) 14:2571&#x2013;8. doi: 10.2147/RMHP.S311638,</Citation><ArticleIdList><ArticleId IdType="doi">10.2147/RMHP.S311638</ArticleId><ArticleId IdType="pmc">PMC8232963</ArticleId><ArticleId IdType="pubmed">34188568</ArticleId></ArticleIdList></Reference><Reference><Citation>Jing MJ, Li H, Li CP, Wei XJ, Lin WQ, Zhu SC, et al. The association between working hours with vigilance and executive function of intensive care unit nurses. J Nurs Manag. (2023) 2023:3770404. doi: 10.1155/2023/3770404,</Citation><ArticleIdList><ArticleId IdType="doi">10.1155/2023/3770404</ArticleId><ArticleId IdType="pmc">PMC11919218</ArticleId><ArticleId IdType="pubmed">40225653</ArticleId></ArticleIdList></Reference><Reference><Citation>Woo SJ, Chae CH, Lim JW. Association between shift work and inflammatory markers in workers at an electronics manufacturing company. Ann Occup Environ Med. (2022) 34:e35. doi: 10.35371/aoem.2022.34.e35,</Citation><ArticleIdList><ArticleId IdType="doi">10.35371/aoem.2022.34.e35</ArticleId><ArticleId IdType="pmc">PMC9748154</ArticleId><ArticleId IdType="pubmed">36544883</ArticleId></ArticleIdList></Reference><Reference><Citation>Chouchou F, Desseilles M. Heart rate variability: a tool to explore the sleeping brain? Front Neurosci. (2014) 8:402. doi: 10.3389/fnins.2014.00402,</Citation><ArticleIdList><ArticleId IdType="doi">10.3389/fnins.2014.00402</ArticleId><ArticleId IdType="pmc">PMC4263095</ArticleId><ArticleId IdType="pubmed">25565936</ArticleId></ArticleIdList></Reference><Reference><Citation>Pumprla J, Howorka K, Groves D, Chester M, Nolan J. Functional assessment of heart rate variability: physiological basis and practical applications. Int J Cardiol. (2002) 84:1&#x2013;14. doi: 10.1016/s0167-5273(02)00057-8,</Citation><ArticleIdList><ArticleId IdType="doi">10.1016/s0167-5273(02)00057-8</ArticleId><ArticleId IdType="pubmed">12104056</ArticleId></ArticleIdList></Reference><Reference><Citation>Yaffe K, Laffan AM, Harrison SL, Redline S, Spira AP, Ensrud KE, et al. Sleep-disordered breathing, hypoxia, and risk of mild cognitive impairment and dementia in older women. JAMA. (2011) 306:613&#x2013;9. doi: 10.1001/jama.2011.1115,</Citation><ArticleIdList><ArticleId IdType="doi">10.1001/jama.2011.1115</ArticleId><ArticleId IdType="pmc">PMC3600944</ArticleId><ArticleId IdType="pubmed">21828324</ArticleId></ArticleIdList></Reference><Reference><Citation>Khan D, Edgell H, Rotondi M, Tamim H. The association between shift work exposure and cognitive impairment among middle-aged and older adults: results from the Canadian longitudinal study on aging (CLSA). PLoS One. (2023) 18:e0289718. doi: 10.1371/journal.pone.0289718,</Citation><ArticleIdList><ArticleId IdType="doi">10.1371/journal.pone.0289718</ArticleId><ArticleId IdType="pmc">PMC10446236</ArticleId><ArticleId IdType="pubmed">37610977</ArticleId></ArticleIdList></Reference><Reference><Citation>Kredlow MA, Capozzoli MC, Hearon BA, Calkins AW, Otto MW. The effects of physical activity on sleep: a meta-analytic review. J Behav Med. (2015) 38:427&#x2013;49. doi: 10.1007/s10865-015-9617-6,</Citation><ArticleIdList><ArticleId IdType="doi">10.1007/s10865-015-9617-6</ArticleId><ArticleId IdType="pubmed">25596964</ArticleId></ArticleIdList></Reference><Reference><Citation>Ueno- Pardi LM, Souza-Duran FL, Matheus L, Rodrigues AG, Barbosa ERF, Cunha PJ, et al. Effects of exercise training on brain metabolism and cognitive functioning in sleep apnea. Sci Rep. (2022) 12:9453. doi: 10.1038/s41598-022-13115-2,</Citation><ArticleIdList><ArticleId IdType="doi">10.1038/s41598-022-13115-2</ArticleId><ArticleId IdType="pmc">PMC9177702</ArticleId><ArticleId IdType="pubmed">35676287</ArticleId></ArticleIdList></Reference><Reference><Citation>Sanaeifar F, Pourranjbar S, Pourranjbar M, Ramezani S, Mehr SR, Wadan AS, et al. Beneficial effects of physical exercise on cognitive-behavioral impairments and brain-derived neurotrophic factor alteration in the limbic system induced by neurodegeneration. Exp Gerontol. (2024) 195:112539. doi: 10.1016/j.exger.2024.112539,</Citation><ArticleIdList><ArticleId IdType="doi">10.1016/j.exger.2024.112539</ArticleId><ArticleId IdType="pubmed">39116955</ArticleId></ArticleIdList></Reference><Reference><Citation>Boini S, Bourgkard E, Ferri&#xe8;res J, Esquirol Y. What do we know about the effect of night-shift work on cardiovascular risk factors? An umbrella review. Front Public Health. (2022) 10:1034195. doi: 10.3389/fpubh.2022.1034195,</Citation><ArticleIdList><ArticleId IdType="doi">10.3389/fpubh.2022.1034195</ArticleId><ArticleId IdType="pmc">PMC9727235</ArticleId><ArticleId IdType="pubmed">36504944</ArticleId></ArticleIdList></Reference><Reference><Citation>Uchida S, Shioda K, Morita Y, Kubota C, Ganeko M, Takeda N. Exercise effects on sleep physiology. Front Neurol. (2012) 3:48. doi: 10.3389/fneur.2012.00048,</Citation><ArticleIdList><ArticleId IdType="doi">10.3389/fneur.2012.00048</ArticleId><ArticleId IdType="pmc">PMC3317043</ArticleId><ArticleId IdType="pubmed">22485106</ArticleId></ArticleIdList></Reference><Reference><Citation>McGinty D, Szymusiak R. Keeping cool: a hypothesis about the mechanisms and functions of slow-wave sleep. Trends Neurosci. (1990) 13:480&#x2013;7. doi: 10.1016/0166-2236(90)90081-K,</Citation><ArticleIdList><ArticleId IdType="doi">10.1016/0166-2236(90)90081-K</ArticleId><ArticleId IdType="pubmed">1703678</ArticleId></ArticleIdList></Reference><Reference><Citation>Kanaley JA, Weltman JY, Veldhuis JD, Rogol AD, Hartman ML, Weltman A. Human growth hormone response to repeated bouts of aerobic exercise. J Appl Physiol. (1997) 83:1756&#x2013;61. doi: 10.1152/jappl.1997.83.5.1756,</Citation><ArticleIdList><ArticleId IdType="doi">10.1152/jappl.1997.83.5.1756</ArticleId><ArticleId IdType="pubmed">9375348</ArticleId></ArticleIdList></Reference><Reference><Citation>Zagaar M, Alhaider I, Dao A, Levine A, Alkarawi A, Alzubaidy M, et al. The beneficial effects of regular exercise on cognition in REM sleep deprivation: behavioral, electrophysiological and molecular evidence. Neurobiol Dis. (2012) 45:1153&#x2013;62. doi: 10.1016/j.nbd.2011.12.039,</Citation><ArticleIdList><ArticleId IdType="doi">10.1016/j.nbd.2011.12.039</ArticleId><ArticleId IdType="pubmed">22227452</ArticleId></ArticleIdList></Reference><Reference><Citation>Abd El-Kader SM, Al-Shreef FM. Inflammatory cytokines and immune system modulation by aerobic versus resisted exercise training for elderly. Afr Health Sci. (2018) 18:120&#x2013;31. doi: 10.4314/ahs.v18i1.16,</Citation><ArticleIdList><ArticleId IdType="doi">10.4314/ahs.v18i1.16</ArticleId><ArticleId IdType="pmc">PMC6016983</ArticleId><ArticleId IdType="pubmed">29977265</ArticleId></ArticleIdList></Reference><Reference><Citation>Ayari S, Abellard A, Carayol M, Guedj &#xc9;, Gavarry O. A systematic review of exercise modalities that reduce pro-inflammatory cytokines in humans and animals&#x2019; models with mild cognitive impairment or dementia. Exp Gerontol. (2023) 175:112141. doi: 10.1016/j.exger.2023.112141,</Citation><ArticleIdList><ArticleId IdType="doi">10.1016/j.exger.2023.112141</ArticleId><ArticleId IdType="pubmed">36898593</ArticleId></ArticleIdList></Reference><Reference><Citation>Monnaatsie M, Biddle SJH, Khan S, Kolbe-Alexander T. Physical activity and sedentary behaviour in shift and non-shift workers: a systematic review and meta-analysis. Prev Med Rep. (2021) 24:101597. doi: 10.1016/j.pmedr.2021.101597,</Citation><ArticleIdList><ArticleId IdType="doi">10.1016/j.pmedr.2021.101597</ArticleId><ArticleId IdType="pmc">PMC8683943</ArticleId><ArticleId IdType="pubmed">34976655</ArticleId></ArticleIdList></Reference><Reference><Citation>Korsh&#xf8;j M, Lund Rasmussen C, de Oliveira ST, Holtermann A, Hallman D. Heart rate during work and heart rate variability during the following night: a day-by-day investigation on the physical activity paradox among blue-collar workers. Scand J Work Environ Health. (2021) 47:387&#x2013;94. doi: 10.5271/sjweh.3965,</Citation><ArticleIdList><ArticleId IdType="doi">10.5271/sjweh.3965</ArticleId><ArticleId IdType="pmc">PMC8259705</ArticleId><ArticleId IdType="pubmed">33929548</ArticleId></ArticleIdList></Reference><Reference><Citation>Holtermann A. Physical activity health paradox: reflections on physical activity guidelines and how to fill research gap. Occup Environ Med. (2022) 79:145&#x2013;6. doi: 10.1136/oemed-2021-108050,</Citation><ArticleIdList><ArticleId IdType="doi">10.1136/oemed-2021-108050</ArticleId><ArticleId IdType="pubmed">34887347</ArticleId></ArticleIdList></Reference><Reference><Citation>Atlantis E, Chow CM, Kirby A, Singh MAF. Worksite intervention effects on sleep quality: a randomized controlled trial. J Occup Health Psychol. (2006) 11:291&#x2013;304. doi: 10.1037/1076-8998.11.4.291,</Citation><ArticleIdList><ArticleId IdType="doi">10.1037/1076-8998.11.4.291</ArticleId><ArticleId IdType="pubmed">17059294</ArticleId></ArticleIdList></Reference><Reference><Citation>Barger LK, Wright KP, Hughes RJ, Czeisler CA. Daily exercise facilitates phase delays of circadian melatonin rhythm in very dim light. Am J Physiol Regul Integr Comp Physiol. (2004) 286:R1077&#x2013;84. doi: 10.1152/ajpregu.00397.2003,</Citation><ArticleIdList><ArticleId IdType="doi">10.1152/ajpregu.00397.2003</ArticleId><ArticleId IdType="pubmed">15031136</ArticleId></ArticleIdList></Reference><Reference><Citation>Barger LK, Sullivan JP, Lockley SW, Czeisler CA. Exposure to short wavelength-enriched white light and exercise improves alertness and performance in operational NASA flight controllers working overnight shifts. J Occup Environ Med. (2021) 63:111&#x2013;8. doi: 10.1097/JOM.0000000000002054</Citation><ArticleIdList><ArticleId IdType="doi">10.1097/JOM.0000000000002054</ArticleId><ArticleId IdType="pubmed">33065729</ArticleId></ArticleIdList></Reference><Reference><Citation>Collins BEG, Hartmann TE, Marino FE, Skein M. The effect of a 12-week mixed-modality training intervention on the cardio-metabolic health of rotational shift workers. J Sci Sport Exerc. (2022) 6:120&#x2013;30. doi: 10.1007/s42978-022-00207-8</Citation><ArticleIdList><ArticleId IdType="doi">10.1007/s42978-022-00207-8</ArticleId></ArticleIdList></Reference><Reference><Citation>Collins BEG, Hartmann TE, Marino FE, Skein M. A comparison of acute high- and moderate-intensity exercise on cardio-metabolic function and sleep among shift workers. J Sci Sport Exerc. (2023) 6:35&#x2013;43. doi: 10.1007/s42978-022-00212-x</Citation><ArticleIdList><ArticleId IdType="doi">10.1007/s42978-022-00212-x</ArticleId></ArticleIdList></Reference><Reference><Citation>Easton D, Gupta C, Vincent G, Vandelanotte C, Duncan M, Tucker P, et al. The relationship between circadian type and physical activity as predictors of cognitive performance during simulated night shifts: a randomised controlled trial. Chronobiol Int. (2025) 42:736&#x2013;54. doi: 10.1080/07420528.2025.2503866,</Citation><ArticleIdList><ArticleId IdType="doi">10.1080/07420528.2025.2503866</ArticleId><ArticleId IdType="pmc">PMC12312784</ArticleId><ArticleId IdType="pubmed">40387143</ArticleId></ArticleIdList></Reference><Reference><Citation>H&#xe4;rm&#xe4; MI, Ilmarinen J, Knauth P, Rutenfranz J, H&#xe4;nninen O. Physical training intervention in female shift workers. I. The effects of intervention on fitness, fatigue, sleep, and psychosomatic symptoms. Ergonomics. (1988) 31:39&#x2013;50. doi: 10.1080/00140138808966647,</Citation><ArticleIdList><ArticleId IdType="doi">10.1080/00140138808966647</ArticleId><ArticleId IdType="pubmed">3359987</ArticleId></ArticleIdList></Reference><Reference><Citation>H&#xe4;rm&#xe4; MI, Ilmarinen J, Knauth P, Rutenfranz J, H&#xe4;nninen O. Physical training intervention in female shift workers. II. The effects of intervention on the circadian rhythms of alertness, short-term memory, and body temperature. Ergonomics. (1988) 31:51&#x2013;63. doi: 10.1080/00140138808966648,</Citation><ArticleIdList><ArticleId IdType="doi">10.1080/00140138808966648</ArticleId><ArticleId IdType="pubmed">3359988</ArticleId></ArticleIdList></Reference><Reference><Citation>Niu S, Lin C, Chen P, Fan Y, Huang H, Chiu H. Immediate and lasting effects of aerobic exercise on the actigraphic sleep parameters of female nurses: a randomized controlled trial. Res Nurs Health. (2021) 44:449&#x2013;57. doi: 10.1002/nur.22126,</Citation><ArticleIdList><ArticleId IdType="doi">10.1002/nur.22126</ArticleId><ArticleId IdType="pubmed">33763879</ArticleId></ArticleIdList></Reference><Reference><Citation>Ha Y, Lee SH, Lee DH, Kang YH, Choi W, An J. Effectiveness of a mobile wellness program for nurses with rotating shifts during the COVID-19 pandemic: a pilot cluster-randomized trial. Int J Environ Res Public Health. (2022) 19:1014. doi: 10.3390/ijerph19021014</Citation><ArticleIdList><ArticleId IdType="doi">10.3390/ijerph19021014</ArticleId><ArticleId IdType="pmc">PMC8776111</ArticleId><ArticleId IdType="pubmed">35055833</ArticleId></ArticleIdList></Reference><Reference><Citation>Sirohi P, Khan MH, Sharma S, Nuhmani S, Al Muslem WH, Abualait T. A systematic review of effects of daytime napping strategies on sports performance in physically active individuals with and without partial-sleep deprivation. PeerJ. (2022) 10:e14460. doi: 10.7717/peerj.14460,</Citation><ArticleIdList><ArticleId IdType="doi">10.7717/peerj.14460</ArticleId><ArticleId IdType="pmc">PMC9744144</ArticleId><ArticleId IdType="pubmed">36518294</ArticleId></ArticleIdList></Reference><Reference><Citation>Folkard S, Arendt J, Clark M. Can melatonin improve shift workers&#x2019; tolerance of the night shift? Some preliminary findings. Chronobiol Int. (1993) 10:315&#x2013;20. doi: 10.3109/07420529309064485,</Citation><ArticleIdList><ArticleId IdType="doi">10.3109/07420529309064485</ArticleId><ArticleId IdType="pubmed">8261530</ArticleId></ArticleIdList></Reference><Reference><Citation>Scott H, Guyett A, Manners J, Stuart N, Kemps E, Toson B, et al. Circadian-informed lighting improves vigilance, sleep, and subjective sleepiness during simulated night-shift work. Sleep. (2024) 47:zsae173. doi: 10.1093/sleep/zsae173,</Citation><ArticleIdList><ArticleId IdType="doi">10.1093/sleep/zsae173</ArticleId><ArticleId IdType="pmc">PMC11543619</ArticleId><ArticleId IdType="pubmed">39078935</ArticleId></ArticleIdList></Reference><Reference><Citation>Sasseville A, Benhaberou-Brun D, Fontaine C, Charon MC, Hebert M. Wearing blue-blockers in the morning could improve sleep of workers on a permanent night schedule: a pilot study. Chronobiol Int. (2009) 26:913&#x2013;25. doi: 10.1080/07420520903044398,</Citation><ArticleIdList><ArticleId IdType="doi">10.1080/07420520903044398</ArticleId><ArticleId IdType="pubmed">19637050</ArticleId></ArticleIdList></Reference><Reference><Citation>Alnawwar MA, Alraddadi MI, Algethmi RA, Salem GA, Salem MA, Alharbi AA. The effect of physical activity on sleep quality and sleep disorder: a systematic review. Cureus. (2023) 15:e43595. doi: 10.7759/cureus.43595,</Citation><ArticleIdList><ArticleId IdType="doi">10.7759/cureus.43595</ArticleId><ArticleId IdType="pmc">PMC10503965</ArticleId><ArticleId IdType="pubmed">37719583</ArticleId></ArticleIdList></Reference><Reference><Citation>Furlan R, Porta A, Costa F, Tank J, Baker L, Schiavi R, et al. (2000). Oscillatory patterns in sympathetic neural discharge and cardiovascular variables during orthostatic stimulus. Circulation. 101, 886&#x2013;892. doi: 10.1161/01.cir.101.8.886</Citation><ArticleIdList><ArticleId IdType="doi">10.1161/01.cir.101.8.886</ArticleId><ArticleId IdType="pubmed">10694528</ArticleId></ArticleIdList></Reference></ReferenceList></PubmedData></PubmedArticle></PubmedArticleSet>